right_rotator.v
module right_rotator 
#(
    parameter N=8
)(
    input [$clog2(N)-1:0] B,
    input [N-1:0] A,
    output [N-1:0] Y
);

// This probably yields better synthesizing result but the code below 'behaves' the same ;)
/*localparam ROWS = $clog2(N);
localparam COLS = N;

wire [(ROWS*COLS)-1:0] A_out;

// at 8 bit we have to shift 4 2 1
// at 4 bits we have to shift 2 1

// 0th row
generate 
        for(genvar j=0; j<COLS; j++) begin : ROW_LOOP
            mux2 mux_I (
                .inp0(A[j]),
                .inp1(1'b0),
                .sel(B[ROWS-1]),
                .out(A_out_first_row[j])
            );
        end 
endgenerate

// other rows
generate 
    for(genvar i=1; i<ROWS; i++) begin : COL_LOOP
        for(genvar j=0; j<COLS; j++) begin : ROW_LOOP
            mux2 mux_I (
                .inp0(A_out[N*(i-1)]),
                .inp1(),
                .sel(),
                .out()
            );
        end 
    end
endgenerate*/

// Right rotator
// TODO: if this does not work change to other answer in:
// https://electronics.stackexchange.com/questions/588602/how-to-rotate-bits-in-verilog
assign Y = (A >> B) | (A << (N-B));

endmodule

right_rotator_tb.v
module right_rotator_tb();

    localparam N = 8;

    reg [N-1:0] A_tb;
    reg [2:0] B_tb;
    wire [N-1:0] Y_tb;

    //
    right_rotator #(
        .N(8) // width
    ) right_rotator
    (
        .B(B_tb),
        .A(A_tb),
        .Y(Y_tb)
    );

    initial begin
        $dumpfile("out/right_rotator.vcd");
        $dumpvars(0, right_rotator_tb);

        A_tb = 8'b0000_1100;

        B_tb = 3'b000;

        #10;

        B_tb = 3'b001;

        #10;

        B_tb = 3'b010;

        #10;

        B_tb = 3'b011;

        #10;

        B_tb = 3'b100;

        #10;

        B_tb = 3'b101;

        #10;

        B_tb = 3'b110;

        #10;

        B_tb = 3'b111;

        #20;
    end

endmodule

out/right_rotator.vcd
$date
	Tue Jul 30 19:31:19 2024
$end
$version
	Icarus Verilog
$end
$timescale
	1s
$end
$scope module right_rotator_tb $end
$var wire 8 ! Y_tb [7:0] $end
$var parameter 32 " N $end
$var reg 8 # A_tb [7:0] $end
$var reg 3 $ B_tb [2:0] $end
$scope module right_rotator $end
$var wire 8 % A [7:0] $end
$var wire 3 & B [2:0] $end
$var wire 8 ' Y [7:0] $end
$var parameter 32 ( N $end
$upscope $end
$upscope $end
$enddefinitions $end
$comment Show the parameter values. $end
$dumpall
b1000 (
b1000 "
$end
#0
$dumpvars
b1100 '
b0 &
b1100 %
b0 $
b1100 #
b1100 !
$end
#10
b110 !
b110 '
b1 $
b1 &
#20
b11 !
b11 '
b10 $
b10 &
#30
b10000001 !
b10000001 '
b11 $
b11 &
#40
b11000000 !
b11000000 '
b100 $
b100 &
#50
b1100000 !
b1100000 '
b101 $
b101 &
#60
b110000 !
b110000 '
b110 $
b110 &
#70
b11000 !
b11000 '
b111 $
b111 &
